happy/__init__.py
happy/cli.py
happy/heroku.py
happy-1.2.1.dist-info/DESCRIPTION.rst
happy-1.2.1.dist-info/METADATA
happy-1.2.1.dist-info/RECORD
happy-1.2.1.dist-info/WHEEL
happy-1.2.1.dist-info/entry_points.txt
happy-1.2.1.dist-info/metadata.json
happy-1.2.1.dist-info/top_level.txt
