Metadata-Version: 2.0
Name: happy
Version: 1.2.1
Summary: Quickly set up and tear down Heroku apps!
Home-page: https://github.com/grampajoe/happy
Author: Joe Friedl
Author-email: joe@joefriedl.net
License: UNKNOWN
Platform: UNKNOWN
Requires-Dist: click
Requires-Dist: requests
